nspider/__init__.py
nspider/abstract/__init__.py
nspider/abstract/process_executor.py
nspider/abstract/process_executor_worker.py
nspider/abstract/singleton.py
nspider/core/__init__.py
nspider/core/log.py
nspider/core/request.py
nspider/core/resource.py
nspider/core/shared_memory_handler.py
nspider/core/spider.py
nspider/core/tps_bucket.py
nspider/core/analyzer/__init__.py
nspider/core/analyzer/analyzer.py
nspider/core/analyzer/analyzer_worker.py
nspider/core/analyzer/parser.py
nspider/core/downloader/__init__.py
nspider/core/downloader/downloader.py
nspider/core/fetcher/__init__.py
nspider/core/fetcher/fetcher.py
nspider/core/fetcher/fetcher_worker.py
nspider/core/proxier/__init__.py
nspider/core/proxier/proxier.py
nspider/core/proxier/proxier_worker.py
nspider/core/scheduler/__init__.py
nspider/core/scheduler/scheduler.py
nspider/settings/__init__.py
nspider/settings/settings.py
nspider/utilities/__init__.py
nspider/utilities/common.py
nspider/utilities/constant.py
nspider/utilities/selector.py
nspider-0.2.0.dist-info/LICENSE.txt
nspider-0.2.0.dist-info/METADATA
nspider-0.2.0.dist-info/WHEEL
nspider-0.2.0.dist-info/top_level.txt
nspider-0.2.0.dist-info/RECORD
