Metadata-Version: 2.1
Name: nspider
Version: 0.2.0
Summary: A light multi-process web resources crawling framework
Home-page: https://github.com/Nymphxyz/nspider
Author: Nymphxyz
Author-email: xyz.hack666@gmail.com
License: MIT
Platform: UNKNOWN
Requires-Dist: requests
Requires-Dist: lxml
Requires-Dist: beautifulsoup4
